[
  {
    "copy-from": "board",
    "id": "board",
    "type": "vehicle_part",
    "name": { "str": "board" },
    "folded_volume": "250 ml",
    "folding_time": "1 seconds",
    "unfolding_time": "1 seconds"
  },
  {
    "copy-from": "halfboard",
    "id": "halfboard",
    "type": "vehicle_part",
    "name": { "str": "quarterpanel" },
    "folded_volume": "250 ml",
    "folding_time": "1 seconds",
    "unfolding_time": "1 seconds"
  },
  {
    "copy-from": "clothboard",
    "id": "clothboard",
    "type": "vehicle_part",
    "name": { "str": "cloth board" },
    "folded_volume": "1 ml",
    "folding_time": "1 seconds",
    "unfolding_time": "1 seconds"
  },
  {
    "copy-from": "stowboard",
    "id": "stowboard",
    "type": "vehicle_part",
    "name": { "str": "stow board" },
    "folded_volume": "250 ml",
    "folding_time": "1 seconds",
    "unfolding_time": "1 seconds"
  },
  {
    "copy-from": "hdstowboard",
    "id": "hdstowboard",
    "type": "vehicle_part",
    "name": { "str": "heavy-duty stow board" },
    "folded_volume": "250 ml",
    "folding_time": "1 seconds",
    "unfolding_time": "1 seconds"
  },
  {
    "copy-from": "hdboard",
    "id": "hdboard",
    "type": "vehicle_part",
    "name": { "str": "heavy-duty board" },
    "folded_volume": "250 ml",
    "folding_time": "1 seconds",
    "unfolding_time": "1 seconds"
  },
  {
    "copy-from": "hdhalfboard",
    "id": "hdhalfboard",
    "type": "vehicle_part",
    "name": { "str": "heavy-duty quarterpanel" },
    "folded_volume": "250 ml",
    "folding_time": "1 seconds",
    "unfolding_time": "1 seconds"
  },
  {
    "copy-from": "woodboard",
    "id": "woodboard",
    "type": "vehicle_part",
    "name": { "str": "wooden board" },
    "folded_volume": "250 ml",
    "folding_time": "1 seconds",
    "unfolding_time": "1 seconds"
  },
  {
    "copy-from": "woodhalfboard",
    "id": "woodhalfboard",
    "type": "vehicle_part",
    "name": { "str": "wooden quarterpanel" },
    "folded_volume": "250 ml",
    "folding_time": "1 seconds",
    "unfolding_time": "1 seconds"
  },
  {
    "copy-from": "xlhalfboard",
    "id": "xlhalfboard",
    "type": "vehicle_part",
    "name": { "str": "extra light quarterpanel" },
    "looks_like": "halfboard",
    "folded_volume": "250 ml",
    "folding_time": "1 seconds",
    "unfolding_time": "1 seconds"
  }
]
